fsm_controller.v
//====================================================
// FSM-based RTL Control Unit
// Author: Suchet
// Description:
//   Synchronous FSM modeling control logic commonly
//   used in SoC / ASIC subsystems.
//====================================================

module fsm_controller (
    input  wire clk,
    input  wire reset,
    input  wire start,
    input  wire done,
    input  wire error,
    output reg  busy,
    output reg  valid,
    output reg  fault
);

    // State encoding
    localparam IDLE  = 3'b000,
               INIT  = 3'b001,
               RUN   = 3'b010,
               DONE  = 3'b011,
               ERROR = 3'b100;

    reg [2:0] current_state, next_state;

    //========================================
    // State Register (Synchronous Reset)
    //========================================
    always @(posedge clk) begin
        if (reset)
            current_state <= IDLE;
        else
            current_state <= next_state;
    end

    //========================================
    // Next-State Logic
    //========================================
    always @(*) begin
        next_state = current_state;
        case (current_state)
            IDLE:  if (start) next_state = INIT;
            INIT:  next_state = RUN;
            RUN:   if (error) next_state = ERROR;
                   else if (done) next_state = DONE;
            DONE:  next_state = DONE;
            ERROR: next_state = ERROR;
            default: next_state = IDLE;
        endcase
    end

    //========================================
    // Output Logic (Moore-style)
    //========================================
    always @(*) begin
        busy  = 1'b0;
        valid = 1'b0;
        fault = 1'b0;

        case (current_state)
            INIT,
            RUN:   busy  = 1'b1;
            DONE:  valid = 1'b1;
            ERROR: fault = 1'b1;
        endcase
    end

endmodule

tb_fsm_controller.v
module tb_fsm_controller;

    reg clk, reset, start, done, error;
    wire busy, valid, fault;

    fsm_controller dut (
        .clk(clk),
        .reset(reset),
        .start(start),
        .done(done),
        .error(error),
        .busy(busy),
        .valid(valid),
        .fault(fault)
    );

    always #5 clk = ~clk;

    initial begin
        $dumpfile("fsm.vcd");
        $dumpvars(0, tb_fsm_controller);

        clk = 0;
        reset = 1;
        start = 0;
        done = 0;
        error = 0;

        #20 reset = 0;
        #10 start = 1;
        #10 start = 0;

        #30 done = 1;
        #10 done = 0;

        #40 reset = 1;
        #10 reset = 0;

        #30 error = 1;
        #10 error = 0;

        #50 $finish;
    end

endmodule

fsm.vcd
$date
	Wed Feb 11 15:49:53 2026
$end
$version
	Icarus Verilog
$end
$timescale
	1s
$end
$scope module tb_fsm_controller $end
$var wire 1 ! valid $end
$var wire 1 " fault $end
$var wire 1 # busy $end
$var reg 1 $ clk $end
$var reg 1 % done $end
$var reg 1 & error $end
$var reg 1 ' reset $end
$var reg 1 ( start $end
$scope module dut $end
$var wire 1 $ clk $end
$var wire 1 % done $end
$var wire 1 & error $end
$var wire 1 ' reset $end
$var wire 1 ( start $end
$var parameter 3 ) DONE $end
$var parameter 3 * ERROR $end
$var parameter 3 + IDLE $end
$var parameter 3 , INIT $end
$var parameter 3 - RUN $end
$var reg 1 # busy $end
$var reg 3 . current_state [2:0] $end
$var reg 1 " fault $end
$var reg 3 / next_state [2:0] $end
$var reg 1 ! valid $end
$upscope $end
$upscope $end
$enddefinitions $end
$comment Show the parameter values. $end
$dumpall
b10 -
b1 ,
b0 +
b100 *
b11 )
$end
#0
$dumpvars
bx /
bx .
0(
1'
0&
0%
0$
x#
x"
x!
$end
#5
0"
0!
0#
b0 /
b0 .
1$
#10
0$
#15
1$
#20
0$
0'
#25
1$
#30
b1 /
0$
1(
#35
1#
b10 /
b1 .
1$
#40
b10 /
0$
0(
#45
1#
b10 .
1$
#50
0$
#55
1$
#60
0$
#65
1$
#70
b11 /
0$
1%
#75
1!
0#
b11 .
1$
#80
0$
0%
#85
1$
#90
0$
#95
1$
#100
0$
#105
1$
#110
0$
#115
1$
#120
0$
1'
#125
0!
b0 /
b0 .
1$
#130
0$
0'
#135
1$
#140
0$
#145
1$
#150
0$
#155
1$
#160
0$
1&
#165
1$
#170
0$
0&
